nidinfo/__init__.py
nidinfo/nid.py
nidinfo/nidinfo.py
haxorsiamnid-1.1.2.dist-info/LICENSE
haxorsiamnid-1.1.2.dist-info/METADATA
haxorsiamnid-1.1.2.dist-info/WHEEL
haxorsiamnid-1.1.2.dist-info/top_level.txt
haxorsiamnid-1.1.2.dist-info/RECORD
